{"cameraMode":{"drawMode":0,"name":"Shaded","section":"Shading Mode"},"sceneLighting":false,"audioPlay":false,"sceneViewState":{"m_AlwaysRefresh":false,"showFog":true,"showSkybox":false,"showFlares":true,"showImageEffects":true,"showParticleSystems":true,"showVisualEffectGraphs":true,"m_FxEnabled":false},"in2DMode":false,"pivot":{"x":1.2801918983459473,"y":1.150902509689331,"z":4.580205917358398},"rotation":{"x":-0.2441720813512802,"y":0.6606714725494385,"z":-0.24169820547103883,"w":-0.6674496531486511},"size":2.232865571975708,"orthographic":false}