{"cameraMode":{"drawMode":0,"name":"Shaded","section":"Shading Mode"},"sceneLighting":false,"audioPlay":false,"sceneViewState":{"m_AlwaysRefresh":false,"showFog":true,"showSkybox":false,"showFlares":true,"showImageEffects":true,"showParticleSystems":true,"showVisualEffectGraphs":true,"m_FxEnabled":false},"in2DMode":false,"pivot":{"x":3.384509325027466,"y":-3.0096688270568849,"z":3.9553027153015138},"rotation":{"x":-0.3057147264480591,"y":-0.1871856153011322,"z":0.06143133342266083,"w":-0.931530773639679},"size":6.160332202911377,"orthographic":false}